{
  "unknown": {
    "versionSfCore": null,
    "versionFramework": "4.1.12",
    "isWithinCompose": false,
    "composeOrgName": null,
    "composeServiceName": null,
    "command": [],
    "options": {},
    "error": null,
    "machineId": "4fea6a43134c825a45b67cb7649f1fcc",
    "serviceProviderAwsCfStackId": null,
    "serviceProviderAwsCfStackCreated": null,
    "serviceProviderAwsCfStackUpdated": null,
    "serviceProviderAwsCfStackStatus": null,
    "serviceProviderAwsCfStackOutputs": null
  }
}